admin_object_actions/__init__.py
admin_object_actions/admin.py
admin_object_actions/apps.py
admin_object_actions/forms.py
admin_object_actions/templates/admin/object_action_form.html
Django_Admin_Object_Actions-0.1.11.dist-info/LICENSE
Django_Admin_Object_Actions-0.1.11.dist-info/METADATA
Django_Admin_Object_Actions-0.1.11.dist-info/WHEEL
Django_Admin_Object_Actions-0.1.11.dist-info/top_level.txt
Django_Admin_Object_Actions-0.1.11.dist-info/RECORD
