Metadata-Version: 2.1
Name: Django-Admin-Object-Actions
Version: 0.1.11
Summary: Library to support object-level actions in the Django admin interface.
Home-page: https://github.com/ninemoreminutes/django-admin-object-actions/
Author: Nine More Minutes, Inc.
Author-email: projects@ninemoreminutes.com
License: BSD
Project-URL: Documentation, https://django-admin-object-actions.rtfd.org/
Project-URL: Source, https://github.com/ninemoreminutes/django-admin-object-actions/
Project-URL: Tracker, https://github.com/ninemoreminutes/django-admin-object-actions/issues
Keywords: django,admin,object,actions
Platform: UNKNOWN
Classifier: Development Status :: 3 - Alpha
Classifier: Environment :: Web Environment
Classifier: Framework :: Django
Classifier: Framework :: Django :: 1.11
Classifier: Framework :: Django :: 2.0
Classifier: Framework :: Django :: 2.1
Classifier: Framework :: Django :: 2.2
Classifier: Framework :: Django :: 3.0
Classifier: Framework :: Django :: 3.1
Classifier: Intended Audience :: Developers
Classifier: License :: OSI Approved :: BSD License
Classifier: Operating System :: OS Independent
Classifier: Programming Language :: Python
Classifier: Programming Language :: Python :: 3
Classifier: Programming Language :: Python :: 3.5
Classifier: Programming Language :: Python :: 3.6
Classifier: Programming Language :: Python :: 3.7
Classifier: Programming Language :: Python :: 3.8
Classifier: Programming Language :: Python :: 3.9
Classifier: Topic :: Internet :: WWW/HTTP
Classifier: Topic :: Software Development :: Libraries
Classifier: Topic :: Software Development :: Libraries :: Python Modules
